auto_ukg/__init__.py
auto_ukg/action_modules.py
auto_ukg/cli.py
auto_ukg-0.1.3.dist-info/METADATA
auto_ukg-0.1.3.dist-info/WHEEL
auto_ukg-0.1.3.dist-info/entry_points.txt
auto_ukg-0.1.3.dist-info/top_level.txt
auto_ukg-0.1.3.dist-info/RECORD
