Metadata-Version: 2.4
Name: auto_ukg
Version: 0.1.3
Summary: Automated tool for interacting with UKG Dimensions
Author: Chris
Requires-Python: >=3.9
Requires-Dist: playwright>=1.43
Requires-Dist: click>=8.1
